Metadata-Version: 1.0
Name: prob-gauss-binomial
Version: 0.2
Summary: Gaussian and Binomial distributions
Home-page: UNKNOWN
Author: Hrithik Malhotra
Author-email: hrithik18236@iiitd.ac.in
License: UNKNOWN
Platform: UNKNOWN
